Metadata-Version: 2.2
Name: mouse2
Version: 0.2.41
Summary: A toolkit for processing molecular dynamics simulation data
Home-page: https://github.com/mglagolev
Author: Mikhail Glagolev, Anna Glagoleva
Author-email: mikhail.glagolev@gmail.com
License: GNU GPL v3
Classifier: Development Status :: 4 - Beta
Classifier: Intended Audience :: Science/Research
Classifier: License :: OSI Approved :: GNU General Public License v3 (GPLv3)
Classifier: Operating System :: POSIX :: Linux
Classifier: Programming Language :: Python :: 3
Requires-Dist: numpy
Requires-Dist: MDAnalysis
Requires-Dist: networkx
Requires-Dist: matplotlib
Requires-Dist: scipy
Requires-Dist: scikit-learn
Requires-Dist: pandas
Requires-Dist: optuna
Requires-Dist: openpyxl
Dynamic: author
Dynamic: author-email
Dynamic: classifier
Dynamic: description
Dynamic: description-content-type
Dynamic: home-page
Dynamic: license
Dynamic: requires-dist
Dynamic: summary
